redact_prompt/__init__.py
redact_prompt-0.1.0.dist-info/METADATA
redact_prompt-0.1.0.dist-info/WHEEL
redact_prompt-0.1.0.dist-info/licenses/LICENSE
redact_prompt-0.1.0.dist-info/RECORD
