Metadata-Version: 2.4
Name: redact-prompt
Version: 0.1.0
Summary: Redact sensitive information (API keys, emails, card info, etc.) from prompts before sending to LLMs
Project-URL: Homepage, https://github.com/Anish-Reddy-K/redact-prompt
Project-URL: Repository, https://github.com/Anish-Reddy-K/redact-prompt
Project-URL: Issues, https://github.com/Anish-Reddy-K/redact-prompt/issues
Author: Anish Reddy
License-Expression: MIT
License-File: LICENSE
Keywords: anthropic,llm,openai,pii,privacy,prompt,redact,security
Classifier: Development Status :: 4 - Beta
Classifier: Intended Audience :: Developers
Classifier: License :: OSI Approved :: MIT License
Classifier: Programming Language :: Python :: 3
Classifier: Programming Language :: Python :: 3.9
Classifier: Programming Language :: Python :: 3.10
Classifier: Programming Language :: Python :: 3.11
Classifier: Programming Language :: Python :: 3.12
Classifier: Programming Language :: Python :: 3.13
Classifier: Programming Language :: Python :: 3.14
Classifier: Topic :: Security
Classifier: Topic :: Software Development :: Libraries :: Python Modules
Requires-Python: >=3.9
Requires-Dist: spacy<4.0.0,>=3.0.0
Provides-Extra: dev
Requires-Dist: pytest>=7.0.0; extra == 'dev'
